d_caching-0.0.1-py3.8-nspkg.pth
devjoyvn/libs/__init__.py
devjoyvn/libs/caching/__init__.py
d_caching-0.0.1.dist-info/METADATA
d_caching-0.0.1.dist-info/WHEEL
d_caching-0.0.1.dist-info/namespace_packages.txt
d_caching-0.0.1.dist-info/top_level.txt
d_caching-0.0.1.dist-info/RECORD
