Metadata-Version: 2.1
Name: d-caching
Version: 0.0.1
Summary: Caching SDK
Home-page: https://github.com/devjoyvn
Author: DEVJOYVN
Author-email: devjoyvn@gmail.com
License: MIT
Keywords: devjoyvn,cache
Classifier: Development Status :: 3 - Alpha
Classifier: Intended Audience :: Developers
Classifier: Topic :: Software Development :: Build Tools
Classifier: License :: OSI Approved :: MIT License
Classifier: Programming Language :: Python :: 3
Classifier: Programming Language :: Python :: 3.6
Classifier: Programming Language :: Python :: 3.7
Classifier: Programming Language :: Python :: 3.8
Classifier: Programming Language :: Python :: 3.9
Classifier: Programming Language :: Python :: 3 :: Only
Requires-Python: >=3
Requires-Dist: redis
